{
  "id": "v1-295965899690-0",
  "name": "Hermes LARGE Shopping Bag for Birkin or Kelly or Constance or Evelyne or Bolide",
  "brand": "Herm\u00e8s",
  "price": "$75",
  "description": "",
  "condition": "New",
  "country": "US",
  "listed_at": "2023-10-04T23:29:24.000Z",
  "source_url": "https://www.ebay.com/itm/295965899690?_skw=hermes+kelly+bag&hash=item44e8f13baa:g:W3wAAOSw2PVlHfSi",
  "platform": "ebay.com",
  "authenticity_label": "counterfeit",
  "search_query": "hermes kelly bag",
  "image_urls": [
    "https://i.ebayimg.com/images/g/W3wAAOSw2PVlHfSi/s-l1600.jpg"
  ],
  "local_images": []
}