{"auth": {"count": 1803, "min": 4, "max": 139401, "median": 3800, "mean": 7903}, "fake": {"count": 1300, "min": 3, "max": 500, "median": 259, "mean": 239}, "band_labels": ["\u20ac0\u2013100", "\u20ac100\u2013250", "\u20ac250\u2013500", "\u20ac500\u20131,000", "\u20ac1,000\u20132,500", "\u20ac2,500\u20135,000", "\u20ac5,000\u201310,000", "\u20ac10,000\u201320,000", "\u20ac20,000\u201350,000"], "auth_bands": [10, 44, 103, 141, 261, 533, 213, 272, 223], "fake_bands": [373, 242, 639, 46, 0, 0, 0, 0, 0], "type_rows": [{"type": "Birkin", "auth_count": 190, "auth_avg": 21555, "fake_count": 219, "fake_avg": 135, "spread": 21420}, {"type": "Kelly", "auth_count": 388, "auth_avg": 14019, "fake_count": 778, "fake_avg": 268, "spread": 13750}, {"type": "Collier", "auth_count": 1, "auth_avg": 12300, "fake_count": 7, "fake_avg": 262, "spread": 12038}, {"type": "Constance", "auth_count": 46, "auth_avg": 11567, "fake_count": 1, "fake_avg": 16, "spread": 11551}, {"type": "Faubourg", "auth_count": 2, "auth_avg": 7800, "fake_count": 0, "fake_avg": 0, "spread": null}, {"type": "Lindy", "auth_count": 16, "auth_avg": 6635, "fake_count": 0, "fake_avg": 0, "spread": null}, {"type": "Sabot", "auth_count": 2, "auth_avg": 6425, "fake_count": 0, "fake_avg": 0, "spread": null}, {"type": "Della Cavalleria", "auth_count": 2, "auth_avg": 5400, "fake_count": 0, "fake_avg": 0, "spread": null}, {"type": "Geta", "auth_count": 9, "auth_avg": 5133, "fake_count": 0, "fake_avg": 0, "spread": null}, {"type": "Roulis", "auth_count": 8, "auth_avg": 5109, "fake_count": 0, "fake_avg": 0, "spread": null}, {"type": "Steeple", "auth_count": 1, "auth_avg": 3800, "fake_count": 0, "fake_avg": 0, "spread": null}, {"type": "Evelyne", "auth_count": 141, "auth_avg": 3677, "fake_count": 1, "fake_avg": 200, "spread": 3477}, {"type": "Picotin", "auth_count": 103, "auth_avg": 3625, "fake_count": 0, "fake_avg": 0, "spread": null}, {"type": "Other", "auth_count": 682, "auth_avg": 3578, "fake_count": 293, "fake_avg": 238, "spread": 3340}, {"type": "Garden Party", "auth_count": 33, "auth_avg": 2973, "fake_count": 0, "fake_avg": 0, "spread": null}, {"type": "Herbag", "auth_count": 151, "auth_avg": 2956, "fake_count": 1, "fake_avg": 43, "spread": 2913}, {"type": "Bolide", "auth_count": 28, "auth_avg": 2068, "fake_count": 0, "fake_avg": 0, "spread": null}], "source_summary": {"vestiairecollective.com": {"count": 1704, "median": 3750, "mean": 8118}, "hermes.com": {"count": 99, "median": 4300, "mean": 4212}, "vinted.de": {"count": 896, "median": 300, "mean": 275}, "ebay.com": {"count": 404, "median": 112, "mean": 157}}, "arbitrage": [{"name": "Herm\u00e8s Mules OZ", "price": "\u20ac390", "price_val": 390.0, "platform": "vinted.de", "url": "https://www.vinted.de/items/8615683255-hermes-mules-oz", "img": "https://images1.vinted.net/tc/05_0172c_LNiAoLxyEimBWLwvuSEXCo6d/1777222512.jpeg?s=332b4f511ca5fa413e8a0735288ef4494c8da09f", "scraped_at": "2026-05-06 03:21:07"}, {"name": "Pendentif Kelly Herm\u00e8s", "price": "\u20ac245", "price_val": 245.0, "platform": "vinted.de", "url": "https://www.vinted.de/items/8825711320-pendentif-kelly-hermes", "img": "https://images1.vinted.net/tc/01_009f8_sd2V1omYM4YxFrph9FvSKfyB/1777915762.jpeg?s=fd78f8449407b76d6120ce226c7fdbea508fbbf6", "scraped_at": "2026-05-06 03:21:03"}, {"name": "Pendentif Kelly laqu\u00e9 Herm\u00e8s", "price": "\u20ac280", "price_val": 280.0, "platform": "vinted.de", "url": "https://www.vinted.de/items/8826507476-pendentif-kelly-laque-hermes", "img": "https://images1.vinted.net/tc/06_01da2_K5yg6bo3cmDnsuYc9w3pefkk/1777919906.jpeg?s=5eec2164e58e00e4ee57f2408bf2a21f5ae644c6", "scraped_at": "2026-05-06 03:21:02"}, {"name": "Bracciale Herm\u00e8s, modello mini clic Kelly, arancio", "price": "\u20ac499", "price_val": 499.0, "platform": "vinted.de", "url": "https://www.vinted.de/items/8829800887-bracciale-hermes-modello-mini-clic-kelly-arancio", "img": "https://images1.vinted.net/tc/05_01022_WksvC4MxZkULXZ16FrXbQmfh/1777974105.jpeg?s=29718673a2e64ed033e92d1555dab07a205a0007", "scraped_at": "2026-05-06 03:21:00"}, {"name": "Bracciale kelly double tour - Herm\u00e8s", "price": "\u20ac400", "price_val": 400.0, "platform": "vinted.de", "url": "https://www.vinted.de/items/8830604641-bracciale-kelly-double-tour-hermes", "img": "https://images1.vinted.net/tc/06_01d51_1BN5YFWyZvWmDfjRY7VMZjBz/1777979520.jpeg?s=e98f189830d890cc7c3091f4ab7018afdaaddbc0", "scraped_at": "2026-05-06 03:20:59"}, {"name": "Ceinture Kelly 18 Herm\u00e8s noir et or", "price": "\u20ac475", "price_val": 475.0, "platform": "vinted.de", "url": "https://www.vinted.de/items/8833047741-ceinture-kelly-18-hermes-noir-et-or", "img": "https://images1.vinted.net/tc/05_010b9_hLM6aCzRbFRRaacfdF6ospR7/1777994412.jpeg?s=a0555e3b681eaa0c2ecc2e6971b03ba24d5f68fc", "scraped_at": "2026-05-06 03:20:57"}, {"name": "Double tour kelly", "price": "\u20ac350", "price_val": 350.0, "platform": "vinted.de", "url": "https://www.vinted.de/items/8833546756-double-tour-kelly", "img": "https://images1.vinted.net/tc/06_01a61_FYja5LE44we9gSzwwLPFYeT1/1777997180.jpeg?s=427dd44fbae111ab2c59d2ec08fe95e3f06f2668", "scraped_at": "2026-05-06 03:20:55"}, {"name": "HERMES Vinyl Kelly Hand Bag Vinyl Clear Auth bs31854", "price": "$368", "price_val": 368.0, "platform": "ebay.com", "url": "https://www.ebay.com/itm/306681642100?_skw=hermes+kelly+bag&hash=item4767a67c74:g:kEEAAeSwUXtpUZAw", "img": "https://i.ebayimg.com/images/g/kEEAAeSwUXtpUZAw/s-l1600.jpg", "scraped_at": "2026-05-06 03:20:37"}, {"name": "HERMES Vinyl Kelly Hand Bag Vinyl Clear Auth bs31863", "price": "$368", "price_val": 368.0, "platform": "ebay.com", "url": "https://www.ebay.com/itm/306681641981?_skw=hermes+kelly+bag&hash=item4767a67bfd:g:A-YAAeSweVlpUZAn", "img": "https://i.ebayimg.com/images/g/A-YAAeSweVlpUZAn/s-l1600.jpg", "scraped_at": "2026-05-06 03:20:37"}, {"name": "Vintage Vogue Purse Pattern 7982 Chanel Hermes Kelly Birkin Bag NEW FF", "price": "$350", "price_val": 350.0, "platform": "ebay.com", "url": "https://www.ebay.com/itm/366390149411?_skw=hermes+kelly+bag&hash=item554e8e0123:g:0nIAAeSwAFFp-iOO", "img": "https://i.ebayimg.com/images/g/0nIAAeSwAFFp-iOO/s-l1600.jpg", "scraped_at": "2026-05-06 03:20:35"}, {"name": "HERMES Vinyl Kelly Bag Handbag Souvenir de L'Exposition 1998 Orange Used Purse", "price": "$294", "price_val": 294.0, "platform": "ebay.com", "url": "https://www.ebay.com/itm/157884392214?_skw=hermes+kelly+bag&hash=item24c2a4a316:g:sIMAAeSwMc9p-Oiu", "img": "https://i.ebayimg.com/images/g/sIMAAeSwMc9p-Oiu/s-l1600.jpg", "scraped_at": "2026-05-06 03:20:35"}, {"name": "HERMES Vinyl Kelly Beach Hand Bag Clear 1997 Exposition Rare Vintage from Japan", "price": "$258", "price_val": 258.0, "platform": "ebay.com", "url": "https://www.ebay.com/itm/366390196847?_skw=hermes+kelly+bag&hash=item554e8eba6f:g:49wAAeSwx-9p-itX", "img": "https://i.ebayimg.com/images/g/49wAAeSwx-9p-itX/s-l1600.jpg", "scraped_at": "2026-05-06 03:20:35"}, {"name": "Ceinture Herm\u00e8s", "price": "\u20ac375", "price_val": 375.0, "platform": "vinted.de", "url": "https://www.vinted.de/items/8758177345-ceinture-hermes", "img": "https://images1.vinted.net/tc/05_01d38_c71RuQRBTLCEow9DC4kQ8UqG/1777231969.jpeg?s=bd030e6802425e55a7afd8427ecf0a859fd382cd", "scraped_at": "2026-05-05 03:13:36"}, {"name": "Ceinture Kelly 18 noir et or - Herm\u00e8s", "price": "\u20ac500", "price_val": 500.0, "platform": "vinted.de", "url": "https://www.vinted.de/items/8819524690-ceinture-kelly-18-noir-et-or-hermes", "img": "https://images1.vinted.net/tc/06_00be1_mSyLJCYbFeq9rM3LJxu4Upej/1777882151.jpeg?s=ea7b75d57aba7233bf38545ff70ea45eeb7c5518", "scraped_at": "2026-05-05 03:13:35"}, {"name": "Hermes Kelly bracelet", "price": "\u20ac455", "price_val": 455.0, "platform": "vinted.de", "url": "https://www.vinted.de/items/8824624466-hermes-kelly-bracelet", "img": "https://images1.vinted.net/tc/05_00bc0_Q3xKvx3mfgpFcpmHhb1cks85/1777910563.jpeg?s=8c5187c3eb49977afc9ef21a625a68b51b873e04", "scraped_at": "2026-05-05 03:13:31"}, {"name": "Hermes empty box for Birkin 35, 40 bag, 47\u00d742\u00d722.4 cm, shipped from Japan.", "price": "$375", "price_val": 375.0, "platform": "ebay.com", "url": "https://www.ebay.com/itm/168259122105?_skw=hermes+birkin+bag&hash=item272d0673b9:g:-ZUAAeSw1rlp-NX7", "img": "https://i.ebayimg.com/images/g/-ZUAAeSw1rlp-NX7/s-l1600.jpg", "scraped_at": "2026-05-05 03:13:19"}, {"name": "Ceinture Hermes Kelly", "price": "\u20ac500", "price_val": 500.0, "platform": "vinted.de", "url": "https://www.vinted.de/items/8819865541-ceinture-hermes-kelly", "img": "https://images1.vinted.net/tc/05_01027_rxZKJSwBp11r4cspzjVZRCnL/1777884733.jpeg?s=f3a2282afbb37d97f7b8ad053edacf6bd826b923", "scraped_at": "2026-05-04 15:22:02"}, {"name": "Montre Vintage Herm\u00e8s - Kelly", "price": "\u20ac475", "price_val": 475.0, "platform": "vinted.de", "url": "https://www.vinted.de/items/8718125734-montre-vintage-hermes-kelly", "img": "https://images1.vinted.net/tc/06_026a1_g4WCSDsyYgBaWPKhQmX5VCWT/1777884134.jpeg?s=ce70c3702458e6b76a3ced2ae5b42ec8e81b1741", "scraped_at": "2026-05-04 15:21:58"}, {"name": "Sandales herm\u00e8s kelly", "price": "\u20ac350", "price_val": 350.0, "platform": "vinted.de", "url": "https://www.vinted.de/items/8817288271-sandales-hermes-kelly", "img": "https://images1.vinted.net/tc/06_008ce_HNVVXZFggXMcAm9EPV83rNV5/1777835124.jpeg?s=c0d1df843f49a7bfd995feb3b774b2019fb7dce5", "scraped_at": "2026-05-04 15:21:57"}, {"name": "Kelly double tour herm\u00e8s vintage 2010", "price": "\u20ac330", "price_val": 330.0, "platform": "vinted.de", "url": "https://www.vinted.de/items/8822119450-kelly-double-tour-hermes-vintage-2010", "img": "https://images1.vinted.net/tc/06_01a91_upQB6yb9H7jMd126g2wsb71t/1777898163.jpeg?s=e50fcad32e592c4c71e2245644ad9e5e70abbc28", "scraped_at": "2026-05-04 15:21:55"}], "total_items": 3103, "total_images": 25808, "concentration": [{"type": "Kelly", "auth_pct": 21.5, "fake_pct": 59.8, "auth_count": 388, "fake_count": 778}, {"type": "Other", "auth_pct": 37.8, "fake_pct": 22.5, "auth_count": 682, "fake_count": 293}, {"type": "Birkin", "auth_pct": 10.5, "fake_pct": 16.8, "auth_count": 190, "fake_count": 219}, {"type": "Collier", "auth_pct": 0.1, "fake_pct": 0.5, "auth_count": 1, "fake_count": 7}, {"type": "Constance", "auth_pct": 2.6, "fake_pct": 0.1, "auth_count": 46, "fake_count": 1}, {"type": "Evelyne", "auth_pct": 7.8, "fake_pct": 0.1, "auth_count": 141, "fake_count": 1}, {"type": "Herbag", "auth_pct": 8.4, "fake_pct": 0.1, "auth_count": 151, "fake_count": 1}, {"type": "Bolide", "auth_pct": 1.6, "fake_pct": 0.0, "auth_count": 28, "fake_count": 0}, {"type": "Della Cavalleria", "auth_pct": 0.1, "fake_pct": 0.0, "auth_count": 2, "fake_count": 0}, {"type": "Faubourg", "auth_pct": 0.1, "fake_pct": 0.0, "auth_count": 2, "fake_count": 0}, {"type": "Garden Party", "auth_pct": 1.8, "fake_pct": 0.0, "auth_count": 33, "fake_count": 0}, {"type": "Geta", "auth_pct": 0.5, "fake_pct": 0.0, "auth_count": 9, "fake_count": 0}], "compression_rows": [{"type": "Constance", "ratio": 722.9, "auth_avg": 11567, "fake_avg": 16}, {"type": "Birkin", "ratio": 159.2, "auth_avg": 21555, "fake_avg": 135}, {"type": "Herbag", "ratio": 68.8, "auth_avg": 2956, "fake_avg": 43}, {"type": "Kelly", "ratio": 52.2, "auth_avg": 14019, "fake_avg": 268}, {"type": "Collier", "ratio": 47.0, "auth_avg": 12300, "fake_avg": 262}, {"type": "Evelyne", "ratio": 18.4, "auth_avg": 3677, "fake_avg": 200}, {"type": "Other", "ratio": 15.1, "auth_avg": 3578, "fake_avg": 238}], "auth_fine_labels": ["\u20ac0k", "\u20ac2k", "\u20ac4k", "\u20ac6k", "\u20ac8k", "\u20ac10k", "\u20ac12k", "\u20ac14k", "\u20ac16k", "\u20ac18k", "\u20ac20k", "\u20ac22k", "\u20ac24k", "\u20ac26k", "\u20ac28k", "\u20ac30k", "\u20ac32k", "\u20ac34k", "\u20ac36k", "\u20ac38k", "\u20ac40k"], "auth_fine_bands": [471, 473, 225, 83, 53, 48, 54, 46, 67, 57, 44, 50, 33, 26, 21, 21, 13, 8, 3, 2, 2], "psych_labels": ["\u20ac0", "\u20ac25", "\u20ac50", "\u20ac75", "\u20ac100", "\u20ac125", "\u20ac150", "\u20ac175", "\u20ac200", "\u20ac225", "\u20ac250", "\u20ac275", "\u20ac300", "\u20ac325", "\u20ac350", "\u20ac375", "\u20ac400", "\u20ac425", "\u20ac450", "\u20ac475", "\u20ac500"], "psych_bands": [127, 92, 81, 73, 48, 35, 50, 30, 45, 34, 65, 62, 82, 56, 95, 84, 72, 24, 62, 37, 46], "img_kb_auth": 0, "img_kb_fake": 0, "img_count_auth": 0, "img_count_fake": 0, "top2_fake_pct": 82.3, "top2_auth_pct": 59.3, "top_compression": {"type": "Constance", "ratio": 722.9, "auth_avg": 11567, "fake_avg": 16}, "fake_platform_stats": {"vinted.de": {"count": 896, "median": 300, "mean": 275, "min": 3, "max": 500}, "ebay.com": {"count": 404, "median": 112, "mean": 157, "min": 4, "max": 400}}, "top_ebay_conditions": [{"condition": "Pre-owned - Good", "count": 126}, {"condition": "New with tags", "count": 118}, {"condition": "Used", "count": 52}, {"condition": "New", "count": 29}, {"condition": "New without tags", "count": 24}, {"condition": "Pre-owned - Excellent", "count": 19}, {"condition": "Open box", "count": 12}, {"condition": "Pre-owned", "count": 6}, {"condition": "Good", "count": 3}, {"condition": "Very Good", "count": 3}], "top_ebay_countries": [{"country": "JP", "count": 166}, {"country": "US", "count": 138}, {"country": "KR", "count": 29}, {"country": "HK", "count": 21}, {"country": "CN", "count": 15}, {"country": "CA", "count": 8}, {"country": "CH", "count": 8}, {"country": "AU", "count": 5}, {"country": "GB", "count": 4}, {"country": "FR", "count": 3}], "ebay_total": 404, "ebay_stats": {"count": 404, "median": 112, "mean": 157, "min": 4, "max": 400}, "vinted_stats": {"count": 896, "median": 300, "mean": 275, "min": 3, "max": 500}, "coverage_rows": [{"platform": "ebay.com", "total": 404, "fields": {"description": {"count": 0, "pct": 0}, "condition": {"count": 404, "pct": 100}, "size": {"count": 0, "pct": 0}, "color": {"count": 0, "pct": 0}, "listed_at": {"count": 404, "pct": 100}, "model": {"count": 0, "pct": 0}, "colors": {"count": 0, "pct": 0}, "country": {"count": 404, "pct": 100}}}, {"platform": "hermes.com", "total": 99, "fields": {"description": {"count": 98, "pct": 99}, "condition": {"count": 98, "pct": 99}, "size": {"count": 0, "pct": 0}, "color": {"count": 0, "pct": 0}, "listed_at": {"count": 16, "pct": 16}, "model": {"count": 16, "pct": 16}, "colors": {"count": 0, "pct": 0}, "country": {"count": 0, "pct": 0}}}, {"platform": "vestiairecollective.com", "total": 1704, "fields": {"description": {"count": 1698, "pct": 100}, "condition": {"count": 0, "pct": 0}, "size": {"count": 0, "pct": 0}, "color": {"count": 0, "pct": 0}, "listed_at": {"count": 1199, "pct": 70}, "model": {"count": 1216, "pct": 71}, "colors": {"count": 1070, "pct": 63}, "country": {"count": 1199, "pct": 70}}}, {"platform": "vinted.de", "total": 896, "fields": {"description": {"count": 0, "pct": 0}, "condition": {"count": 350, "pct": 39}, "size": {"count": 52, "pct": 6}, "color": {"count": 0, "pct": 0}, "listed_at": {"count": 0, "pct": 0}, "model": {"count": 0, "pct": 0}, "colors": {"count": 0, "pct": 0}, "country": {"count": 0, "pct": 0}}}], "top_models": [{"model": "Herbag", "count": 145}, {"model": "Kelly 28", "count": 114}, {"model": "Picotin", "count": 103}, {"model": "Kelly", "count": 90}, {"model": "Birkin 30", "count": 84}, {"model": "Mini Evelyne", "count": 79}, {"model": "Kelly 32", "count": 71}, {"model": "Birkin 35", "count": 65}, {"model": "Evelyne", "count": 61}, {"model": "Constance", "count": 43}, {"model": "Kelly 25", "count": 35}, {"model": "Birkin 25", "count": 33}], "top_countries": [{"country": "United States", "count": 1106}, {"country": "France", "count": 36}, {"country": "Italy", "count": 19}, {"country": "Germany", "count": 8}, {"country": "United Kingdom", "count": 7}, {"country": "Spain", "count": 5}, {"country": "CN", "count": 5}, {"country": "Netherlands", "count": 2}, {"country": "SG", "count": 2}, {"country": "Hong Kong", "count": 2}], "top_conditions": [{"condition": "Sehr gut", "count": 164}, {"condition": "Pre-owned - Good", "count": 126}, {"condition": "New with tags", "count": 118}, {"condition": "Neu, mit Etikett", "count": 78}, {"condition": "Neu", "count": 63}, {"condition": "Used", "count": 52}, {"condition": "Gut", "count": 38}, {"condition": "New", "count": 29}], "desc_auth": {"count": 1796, "mean": 575, "median": 587}, "desc_fake": {"count": 0, "mean": 0, "median": 0}, "timeline": {"labels": ["2018-11", "2019-02", "2019-03", "2019-06", "2019-08", "2019-11", "2020-03", "2020-08", "2020-09", "2020-11", "2021-02", "2021-05", "2021-09", "2021-10", "2021-11", "2022-02", "2022-06", "2022-08", "2022-09", "2022-10", "2022-11", "2022-12", "2023-01", "2023-03", "2023-04", "2023-07", "2023-08", "2023-09", "2023-10", "2023-11", "2023-12", "2024-01", "2024-02", "2024-03", "2024-04", "2024-05", "2024-06", "2024-07", "2024-08", "2024-09", "2024-10", "2024-11", "2024-12", "2025-01", "2025-02", "2025-03", "2025-04", "2025-05", "2025-06", "2025-07", "2025-08", "2025-09", "2025-10", "2025-11", "2025-12", "2026-01", "2026-02", "2026-03", "2026-04", "2026-05"], "auth": [0, 0, 0, 0, 0, 0, 0, 0, 0, 0, 0, 0, 0, 0, 0, 0, 0, 0, 0, 0, 0, 0, 0, 0, 0, 0, 0, 0, 0, 0, 0, 0, 0, 0, 0, 0, 1, 0, 0, 0, 0, 0, 0, 1, 0, 1, 1, 2, 6, 6, 6, 8, 8, 23, 30, 32, 59, 234, 480, 217], "fake": [3, 1, 1, 1, 2, 2, 3, 1, 1, 1, 2, 4, 1, 3, 1, 4, 1, 1, 1, 1, 4, 6, 2, 10, 9, 1, 1, 2, 5, 1, 5, 3, 3, 1, 4, 1, 1, 3, 1, 2, 1, 1, 4, 8, 6, 2, 5, 10, 9, 9, 10, 12, 11, 9, 19, 13, 24, 43, 91, 17]}, "total_with_metadata": 2550}